{
  "@easy_qa_jobs": 2235,
  "@remote_jobs_relocate": 1032,
  "@zarubezhom_jobs": 3984,
  "@jobs_in_it_remoute": 37521,
  "@HRTech_Jobs": 2674,
  "@it_jobs_agregator": 287551,
  "@revacancy": 150380,
  "@jobsearchIT": 83222,
  "@it_vakansii_jobs": 3080,
  "@remotejun": 5186,
  "@qa_jobs_rabota": 556,
  "@Remoteit": 13490,
  "@newdirections": 6793,
  "@refer_me_it": 711,
  "@jun_qa": 1047,
  "@itvacancykz": 1859,
  "@jobfortm": 4799,
  "@aitujobs": 801,
  "@datajobschannel": 3647,
  "@analitiki_rabota": 1142,
  "@data_analysis_jobs": 3839,
  "@jtbl_vacancy": 3685,
  "itcom_kz": 6890,
  "runello_rus_datascience": 3357,
  "foranalysts": 10575,
  "JobOfferInside": 2252,
  "nodatanojobs": 589,
  "remote_kazakhstan": 727,
  "data_hr": 1335,
  "vacancy_cs": 827
}